{"cookies": [{"name": "_SSV", "value": "4d59b49b9fdf15b3f4666371cbcedafd", "domain": "riskmanagement.lexisnexis.com", "path": "/app/bps/", "expires": -1, "httpOnly": true, "secure": true, "sameSite": "Lax"}, {"name": "_SESSION_ID_COOKIE", "value": "63c627633dfec6880f540c2933d081ac", "domain": "riskmanagement.lexisnexis.com", "path": "/app/bps/", "expires": -1, "httpOnly": true, "secure": true, "sameSite": "Lax"}, {"name": "_MFA_COOKIE", "value": "52616e646f6d495671692cddea9ea269b0dc463e3c96dbf8871967be4c6caf2e8ff256d061d783e077a259ffb8d658b372a20505390f0ccd", "domain": "riskmanagement.lexisnexis.com", "path": "/app/bps", "expires": 1729444165.591249, "httpOnly": true, "secure": true, "sameSite": "Lax"}, {"name": "thx_guid", "value": "f6d1224457e9f1c5b59d739857062baf", "domain": "h.online-metrix.net", "path": "/", "expires": 1754834061.59061, "httpOnly": true, "secure": true, "sameSite": "None"}, {"name": "tmx_guid", "value": "AAwsYtm0IjV0-kY2_bGkbtbI1T-fDXmxWjnk_RjmDLR2f6JytnOsB5dF3nUdofgo7zMUSCk-ynASlrTsBy3w0xkduSMhvg", "domain": "h.online-metrix.net", "path": "/", "expires": 1757220007.386036, "httpOnly": true, "secure": true, "sameSite": "None"}], "origins": [{"origin": "https://riskmanagement.lexisnexis.com", "localStorage": [{"name": "mainWinName", "value": "rskm1722660008325"}, {"name": "_pendo_guides_blocked.ec5df5ae-302b-4b28-5f32-2738111fe6a7", "value": "{\"ttl\":1722674409872,\"value\":\"0\"}"}, {"name": "_pendo_visitorId.ec5df5ae-302b-4b28-5f32-2738111fe6a7", "value": "{\"ttl\":1731300016478,\"value\":\"19153104\"}"}, {"name": "ed73f20edbf2b73", "value": "357783e5db294139b9d72efc1dcee288_1875825254374"}, {"name": "_pendo_accountId.ec5df5ae-302b-4b28-5f32-2738111fe6a7", "value": "{\"ttl\":1731300016478,\"value\":\"7048779\"}"}, {"name": "_pendo_meta.ec5df5ae-302b-4b28-5f32-2738111fe6a7", "value": "{\"ttl\":1731300009168,\"value\":3048409684}"}]}]}